{
  "subSceneId": "daily_019_sub_2",
  "subSceneName": "询问推荐",
  "questionType": "choice",
  "exportedAt": "2026-03-14T13:52:43.490Z",
  "questions": [
    {
      "id": "daily_019_sub_2_choice_1",
      "subSceneId": "daily_019_sub_2",
      "type": "choice",
      "order": 1,
      "content": {
        "type": "choice",
        "options": [
          {
            "id": "opt_1",
            "text": "How about a soft pink peony arrangement with some lavender? It’s gentle and within your budget.",
            "isCorrect": true
          },
          {
            "id": "opt_2",
            "text": "Do you have any discounts on chocolate? I think she’d like that more.",
            "isCorrect": false
          },
          {
            "id": "opt_3",
            "text": "I don’t know what she likes—I’ll just pick the most expensive one.",
            "isCorrect": false
          },
          {
            "id": "opt_4",
            "text": "Why don’t you ask her what she wants? Maybe she’ll tell you.",
            "isCorrect": false
          }
        ],
        "situation": "顾客想为母亲买一束花庆祝母亲节，希望花束温馨但不夸张，预算中等。",
        "explanation": "正确答案精准回应了顾客对花束风格（温馨不夸张）和预算（约40美元）的需求，使用自然推荐表达。干扰项1答非所问，转向巧克力；干扰项2误解了顾客意图，认为应选最贵的；干扰项3回避责任，不符合服务场景中的积极推荐角色。",
        "speakerText": "I'm looking for a bouquet for my mom for Mother's Day—something warm but not too flashy, and around $40.",
        "dialogueMode": "user_responds",
        "speakerTextCn": "我想找一束花送给妈妈庆祝母亲节，要温馨但不夸张，预算大约40美元。"
      }
    }
  ]
}