{
  "subSceneId": "daily_027_sub_4",
  "subSceneName": "了解保修",
  "questionType": "fill_blank",
  "exportedAt": "2026-03-14T13:52:43.622Z",
  "questions": [
    {
      "id": "daily_027_sub_4_fill_blank_1",
      "subSceneId": "daily_027_sub_4",
      "type": "fill_blank",
      "order": 1,
      "content": {
        "hint": "当对方说只保制造缺陷时，意外损坏通常用 'not covered' 表达",
        "type": "fill_blank",
        "blanks": [
          {
            "index": 0,
            "answer": "not covered",
            "options": [
              "not covered",
              "free to fix",
              "included in the price",
              "covered under insurance"
            ]
          }
        ],
        "situation": "你在电子产品商店购买了一台新耳机，销售员说明保修政策，你想确认是否包含意外摔坏的情况。",
        "speakerText": "The warranty covers manufacturing defects only, not physical damage from drops or water.",
        "dialogueMode": "user_responds",
        "speakerTextCn": "保修仅涵盖制造缺陷，不包括因掉落或进水造成的物理损坏。",
        "knowledgePoint": "保修范围的否定表达",
        "responseTemplate": "So, if I accidentally drop it and the earcup breaks, that's ___?"
      }
    }
  ]
}