{
  "subSceneId": "daily_028_sub_3",
  "subSceneName": "确认价格和购买",
  "questionType": "speaking",
  "exportedAt": "2026-03-14T13:52:43.642Z",
  "questions": [
    {
      "id": "daily_028_sub_3_speaking_3",
      "subSceneId": "daily_028_sub_3",
      "type": "speaking",
      "order": 3,
      "content": {
        "qaId": null,
        "type": "speaking",
        "speakerText": "The total is $22.45. Would you like to buy it?",
        "dialogueMode": "user_responds",
        "speakerTextCn": "总价是22.45美元，您要购买吗？",
        "expectedAnswers": [
          "Yes, I'll take it.",
          "Okay, I'll go ahead and buy it.",
          "Perfect, I'll pay with cash."
        ],
        "evaluationCriteria": [
          "意图达成度：明确表达购买决定",
          "语言准确性：使用正确的动词搭配（take, buy）和支付方式表达",
          "表达自然度：使用口语化连接词如 'go ahead', 'perfect'，体现真实对话节奏"
        ]
      }
    }
  ]
}