{
  "subSceneId": "social_080_sub_2",
  "subSceneName": "询问计划",
  "questionType": "choice",
  "exportedAt": "2026-03-14T13:52:43.752Z",
  "questions": [
    {
      "id": "social_080_sub_2_choice_3",
      "subSceneId": "social_080_sub_2",
      "type": "choice",
      "order": 3,
      "content": {
        "qaId": null,
        "type": "choice",
        "options": [
          {
            "id": "opt_1",
            "text": "I'm cooking a turkey with my cousins.",
            "isCorrect": true
          },
          {
            "id": "opt_2",
            "text": "I think the store is open.",
            "isCorrect": false
          },
          {
            "id": "opt_3",
            "text": "I need to pay my rent.",
            "isCorrect": false
          },
          {
            "id": "opt_4",
            "text": "Thanksgiving is in November.",
            "isCorrect": false
          }
        ],
        "explanation": "正确答案直接回应了节日安排，使用了符合文化背景的表达 'cooking a turkey with my cousins'，自然且具体。其他选项要么是无关事实（如月份）、要么是生活事务，未体现假期计划的核心意图。",
        "speakerText": "Do you have anything planned for Thanksgiving?",
        "dialogueMode": "user_responds",
        "speakerTextCn": "感恩节你有安排吗？"
      }
    }
  ]
}