{
  "subSceneId": "social_083_sub_3",
  "subSceneName": "询问携带物品",
  "questionType": "choice",
  "exportedAt": "2026-03-14T13:52:43.794Z",
  "questions": [
    {
      "id": "social_083_sub_3_choice_3",
      "subSceneId": "social_083_sub_3",
      "type": "choice",
      "order": 3,
      "content": {
        "qaId": null,
        "type": "choice",
        "options": [
          {
            "id": "opt_1",
            "text": "Bring a blanket and some fruit if you want.",
            "isCorrect": true
          },
          {
            "id": "opt_2",
            "text": "I don't care what you bring, just come.",
            "isCorrect": false
          },
          {
            "id": "opt_3",
            "text": "You must bring a knife and fork.",
            "isCorrect": false
          },
          {
            "id": "opt_4",
            "text": "I'll send you a list later.",
            "isCorrect": false
          }
        ],
        "explanation": "正确答案 'Bring a blanket and some fruit if you want.' 是礼貌且具体的建议，既给出选项又不强求，符合场景要求。选项B语气生硬，选项C过于强制，选项D拖延决策，均不符合轻松明确的社交回应标准。",
        "speakerText": "Do you need me to bring anything for the picnic?",
        "dialogueMode": "user_responds",
        "speakerTextCn": "野餐需要我带点什么吗？"
      }
    }
  ]
}