{
  "subSceneId": "social_094_sub_1",
  "subSceneName": "初次问候",
  "questionType": "choice",
  "exportedAt": "2026-03-08T15:38:56.797Z",
  "questions": [
    {
      "id": "social_094_sub_1_qa_1_choice_1",
      "subSceneId": "social_094_sub_1",
      "type": "choice",
      "order": 1,
      "content": {
        "qaId": "social_094_sub_1_qa_1",
        "type": "choice",
        "options": [
          {
            "id": "opt_1",
            "text": "Hey, I'm Alex. What's your name?",
            "isCorrect": true
          },
          {
            "id": "opt_2",
            "text": "你好，我是Alex。这里的环境很好！",
            "isCorrect": false
          },
          {
            "id": "opt_3",
            "text": "Sorry, I'm Alex. Can you speak English?",
            "isCorrect": false
          },
          {
            "id": "opt_4",
            "text": "Hi, I'm Alex. I love your shirt.",
            "isCorrect": false
          }
        ],
        "explanation": "正确答案\"Hey, I'm Alex. What's your name?\"是因为它在问候后直接询问对方的姓名，这是初次问候时常见的对话方式。其他选项不正确，因为它们没有直接询问对方的姓名或信息，或者询问了不相关的问题。",
        "dialogueMode": "user_asks",
        "scenarioHint": "在破冰聊天中，主动发起问候是常见的开场方式。"
      }
    },
    {
      "id": "social_094_sub_1_choice_2",
      "subSceneId": "social_094_sub_1",
      "type": "choice",
      "order": 2,
      "content": {
        "qaId": null,
        "type": "choice",
        "options": [
          {
            "id": "opt_1",
            "text": "Yeah, I'm Taylor. Nice to meet you!",
            "isCorrect": true
          },
          {
            "id": "opt_2",
            "text": "I don't know you. Who are you?",
            "isCorrect": false
          },
          {
            "id": "opt_3",
            "text": "Yes, I'm here for the conference. The food is good.",
            "isCorrect": false
          },
          {
            "id": "opt_4",
            "text": "Maybe. Are you from here?",
            "isCorrect": false
          }
        ],
        "explanation": "正确答案直接回应了对方的问候并做了自我介绍，符合初次见面的社交规范。选项2语气生硬，选项3未回应身份确认，选项4反问但未完成自我介绍，不够完整。",
        "speakerText": "Hi there! I'm Sam. You must be new here?",
        "dialogueMode": "user_responds",
        "speakerTextCn": "嗨！我是Sam。你应该是新来的吧？"
      }
    },
    {
      "id": "social_094_sub_1_choice_3",
      "subSceneId": "social_094_sub_1",
      "type": "choice",
      "order": 3,
      "content": {
        "qaId": null,
        "type": "choice",
        "options": [
          {
            "id": "opt_1",
            "text": "Same here! I'm Mia. Hope we find some good talks!",
            "isCorrect": true
          },
          {
            "id": "opt_2",
            "text": "Oh, really? I didn't notice you.",
            "isCorrect": false
          },
          {
            "id": "opt_3",
            "text": "The event is over in an hour.",
            "isCorrect": false
          },
          {
            "id": "opt_4",
            "text": "I'm busy right now. Talk later.",
            "isCorrect": false
          }
        ],
        "explanation": "正确答案用 'Same here!' 建立共鸣，同时自我介绍并表达积极期待，是自然的社交回应。选项2冷漠，选项3无关，选项4不礼貌，都破坏了建立联系的初衷。",
        "speakerText": "Hey, I'm Leo. This is my first time at this event.",
        "dialogueMode": "user_responds",
        "speakerTextCn": "嗨，我是Leo。这是我第一次来这个活动。"
      }
    }
  ]
}