{
  "subSceneId": "study_abroad_102_sub_1",
  "subSceneName": "互相打招呼",
  "questionType": "fill_blank",
  "exportedAt": "2026-03-08T15:38:56.888Z",
  "questions": [
    {
      "id": "study_abroad_102_sub_1_qa_2_fill_blank_1",
      "subSceneId": "study_abroad_102_sub_1",
      "type": "fill_blank",
      "order": 1,
      "content": {
        "hint": "表达'属于某个团队或项目'时，常用 'be part of'",
        "qaId": "study_abroad_102_sub_1_qa_2",
        "type": "fill_blank",
        "blanks": [
          {
            "index": 0,
            "answer": "part of",
            "options": [
              "part of",
              "in the",
              "doing",
              "join"
            ]
          }
        ],
        "dialogueMode": "user_asks",
        "scenarioHint": "小组成员初次见面寒暄并确认身份，你想知道对方是否也是这个项目的成员",
        "knowledgePoint": "表达归属关系的常用句型",
        "responseTemplate": "Hi, I'm Alex. Are you___this project?"
      }
    },
    {
      "id": "study_abroad_102_sub_1_qa_1_fill_blank_1",
      "subSceneId": "study_abroad_102_sub_1",
      "type": "fill_blank",
      "order": 1,
      "content": {
        "hint": "在口语中，表示确认的常用结尾是 'right?'，用于寻求对方认同",
        "qaId": "study_abroad_102_sub_1_qa_1",
        "type": "fill_blank",
        "blanks": [
          {
            "index": 0,
            "answer": "right",
            "options": [
              "right",
              "isn't it",
              "aren't you",
              "don't you"
            ]
          }
        ],
        "dialogueMode": "user_asks",
        "scenarioHint": "用户在小组初次见面时，想确认对方是否和自己属于同一组，需要使用一个自然的疑问句来询问",
        "knowledgePoint": "日常对话中的确认性问句结构",
        "responseTemplate": "Hey everyone, I'm [name]. You're all in the same group, ___?"
      }
    },
    {
      "id": "study_abroad_102_sub_1_fill_blank_1",
      "subSceneId": "study_abroad_102_sub_1",
      "type": "fill_blank",
      "order": 1,
      "content": {
        "hint": "回应时需包含自己的名字和国籍，结构为 'I'm [名字] from [国家]'",
        "type": "fill_blank",
        "blanks": [
          {
            "index": 0,
            "answer": "Sarah",
            "options": [
              "Sarah",
              "from Canada",
              "a student",
              "happy to be here"
            ]
          },
          {
            "index": 1,
            "answer": "Canada",
            "options": [
              "Canada",
              "the team",
              "a good person",
              "very excited"
            ]
          }
        ],
        "situation": "在小组活动中，新成员们第一次见面，其中一人主动介绍自己，其他人需要回应并做自我介绍。",
        "speakerText": "Hi everyone, I'm Alex from Brazil. Nice to meet you all!",
        "dialogueMode": "user_responds",
        "speakerTextCn": "大家好，我是来自巴西的Alex，很高兴认识你们！",
        "knowledgePoint": "自我介绍的基本结构",
        "responseTemplate": "Hi Alex, I'm ___ from ___. Nice to meet you too!"
      }
    },
    {
      "id": "study_abroad_102_sub_1_fill_blank_2",
      "subSceneId": "study_abroad_102_sub_1",
      "type": "fill_blank",
      "order": 2,
      "content": {
        "hint": "表达共鸣后，应使用礼貌性寒暄语收尾，增强互动感",
        "type": "fill_blank",
        "blanks": [
          {
            "index": 0,
            "answer": "Great to meet you!",
            "options": [
              "Great to meet you!",
              "I know that place.",
              "I like Australia.",
              "Same here."
            ]
          }
        ],
        "situation": "在团队破冰环节，一位成员刚说完自己的名字，另一位成员想表达认同并拉近距离。",
        "speakerText": "I'm Jamie from Australia.",
        "dialogueMode": "user_responds",
        "speakerTextCn": "我是来自澳大利亚的Jamie。",
        "knowledgePoint": "表达认同后的自然回应",
        "responseTemplate": "Oh, really? I'm from the same place! ___"
      }
    },
    {
      "id": "study_abroad_102_sub_1_fill_blank_3",
      "subSceneId": "study_abroad_102_sub_1",
      "type": "fill_blank",
      "order": 3,
      "content": {
        "hint": "不要只说'Yes'，要结合名字和积极情绪表达，让回应更温暖",
        "type": "fill_blank",
        "blanks": [
          {
            "index": 0,
            "answer": "Liam",
            "options": [
              "Liam",
              "in Group 3",
              "ready to work",
              "not sure"
            ]
          }
        ],
        "situation": "小组成员互相认识时，有人用简短方式确认彼此是否同组，其他人需用完整句回应以建立联系。",
        "speakerText": "So we're all in Group 3, right?",
        "dialogueMode": "user_responds",
        "speakerTextCn": "所以我们都是第三组的，对吧？",
        "knowledgePoint": "避免简单yes/no，使用完整句增强人际连接",
        "responseTemplate": "Yep, I'm ___ and I'm glad we're together!"
      }
    },
    {
      "id": "study_abroad_102_sub_1_pq_6",
      "subSceneId": "study_abroad_102_sub_1",
      "type": "fill_blank",
      "order": 6,
      "content": {
        "hint": "口语中表示‘我都行’的非正式表达",
        "qaId": null,
        "type": "fill_blank",
        "blanks": [
          {
            "index": 0,
            "answer": "down",
            "options": [
              "down",
              "ready",
              "happy",
              "willing"
            ]
          }
        ],
        "template": "I'm ______ for anything. Let's just get started!",
        "dialogueMode": "user_responds",
        "knowledgePoint": "口语固定表达：I'm down for anything（我都可以）"
      }
    }
  ]
}