{
  "subSceneId": "travel_057_sub_4",
  "subSceneName": "登机指引",
  "questionType": "fill_blank",
  "exportedAt": "2026-03-08T15:38:57.076Z",
  "questions": [
    {
      "id": "travel_057_sub_4_fill_blank_1",
      "subSceneId": "travel_057_sub_4",
      "type": "fill_blank",
      "order": 1,
      "content": {
        "hint": "表达‘已准备好’最自然的搭配是 'have ... ready'",
        "type": "fill_blank",
        "blanks": [
          {
            "index": 0,
            "answer": "ready",
            "options": [
              "prepared",
              "ready",
              "in hand",
              "available"
            ]
          }
        ],
        "situation": "地勤人员通知你登机前需要出示登机牌和身份证件，你需确认自己已准备好。",
        "speakerText": "Please have your boarding pass and ID ready before boarding.",
        "dialogueMode": "user_responds",
        "speakerTextCn": "登机前请准备好您的登机牌和身份证件。",
        "knowledgePoint": "常用搭配：have something ready",
        "responseTemplate": "I've got them ___"
      }
    },
    {
      "id": "travel_057_sub_4_fill_blank_2",
      "subSceneId": "travel_057_sub_4",
      "type": "fill_blank",
      "order": 2,
      "content": {
        "hint": "表达‘保持安静’最常用的是 'stay quiet'，'remain' 虽正确但较少用于口语回应",
        "type": "fill_blank",
        "blanks": [
          {
            "index": 0,
            "answer": "stay",
            "options": [
              "stay",
              "keep",
              "be",
              "remain"
            ]
          }
        ],
        "situation": "地勤人员提醒你登机时需保持安静并跟随队伍，你需回应表示会遵守。",
        "speakerText": "Please remain quiet and follow the line as we board.",
        "dialogueMode": "user_responds",
        "speakerTextCn": "登机时请保持安静并按顺序排队。",
        "knowledgePoint": "日常口语中的行为指令回应",
        "responseTemplate": "I'll ___ quietly and follow the line."
      }
    },
    {
      "id": "travel_057_sub_4_fill_blank_3",
      "subSceneId": "travel_057_sub_4",
      "type": "fill_blank",
      "order": 3,
      "content": {
        "hint": "表示‘正在前往’登机口，最自然的口语表达是 'heading to the gate'",
        "type": "fill_blank",
        "blanks": [
          {
            "index": 0,
            "answer": "heading",
            "options": [
              "heading",
              "going",
              "coming",
              "moving"
            ]
          }
        ],
        "situation": "地勤人员告知你登机口即将关闭，提醒你尽快登机，你需快速回应确认。",
        "speakerText": "The gate is closing soon — please board now.",
        "dialogueMode": "user_responds",
        "speakerTextCn": "登机口即将关闭，请立即登机。",
        "knowledgePoint": "表示即时行动的口语动词选择",
        "responseTemplate": "Got it, I'm ___ now."
      }
    },
    {
      "id": "travel_057_sub_4_pq_4",
      "subSceneId": "travel_057_sub_4",
      "type": "fill_blank",
      "order": 4,
      "content": {
        "hint": "表示‘在……附近’的常用介词",
        "qaId": "travel_057_sub_4_qa_1",
        "type": "fill_blank",
        "blanks": [
          {
            "index": 0,
            "answer": "near",
            "options": [
              "near",
              "next",
              "at",
              "by"
            ]
          }
        ],
        "template": "Boarding starts in 5 minutes — please wait ___ the gate.",
        "dialogueMode": "user_responds",
        "knowledgePoint": "介词用法（near 表示靠近但不直接在门口）"
      }
    },
    {
      "id": "travel_057_sub_4_pq_5",
      "subSceneId": "travel_057_sub_4",
      "type": "fill_blank",
      "order": 5,
      "content": {
        "hint": "登机组别通常用数字表示，而非序数词",
        "qaId": "travel_057_sub_4_qa_2",
        "type": "fill_blank",
        "blanks": [
          {
            "index": 0,
            "answer": "3",
            "options": [
              "3",
              "three",
              "third",
              "3rd"
            ]
          }
        ],
        "template": "We'll call priority passengers first — you're in group ___.",
        "dialogueMode": "user_responds",
        "knowledgePoint": "场景高频词汇（登机组别表达）"
      }
    },
    {
      "id": "travel_057_sub_4_pq_6",
      "subSceneId": "travel_057_sub_4",
      "type": "fill_blank",
      "order": 6,
      "content": {
        "hint": "登机时必须出示的纸质或电子凭证",
        "qaId": null,
        "type": "fill_blank",
        "blanks": [
          {
            "index": 0,
            "answer": "boarding pass",
            "options": [
              "boarding pass",
              "ticket",
              "passport",
              "luggage tag"
            ]
          }
        ],
        "template": "Please have your ___ and ID ready when your group is called.",
        "dialogueMode": "user_responds",
        "knowledgePoint": "场景核心词汇（boarding pass 登机牌）"
      }
    }
  ]
}