{
  "subSceneId": "travel_066_sub_1",
  "subSceneName": "打招呼请求兑换",
  "questionType": "choice",
  "exportedAt": "2026-03-08T15:38:57.172Z",
  "questions": [
    {
      "id": "travel_066_sub_1_qa_1_choice_1",
      "subSceneId": "travel_066_sub_1",
      "type": "choice",
      "order": 1,
      "content": {
        "qaId": "travel_066_sub_1_qa_1",
        "type": "choice",
        "options": [
          {
            "id": "opt_1",
            "text": "Hi there! Can I exchange some USD for euros?",
            "isCorrect": true
          },
          {
            "id": "opt_2",
            "text": "How much is one euro?",
            "isCorrect": false
          },
          {
            "id": "opt_3",
            "text": "I want euros now.",
            "isCorrect": false
          },
          {
            "id": "opt_4",
            "text": "Do you exchange money?",
            "isCorrect": false
          }
        ],
        "explanation": "正确答案是选项1，因为它礼貌、自然且明确表达了兑换请求，符合场景需求。选项2只询问汇率，未提出兑换请求；选项3语气生硬且不礼貌，缺乏基本礼貌用语；选项4虽然语法正确，但只是确认服务是否存在，未明确表达具体兑换需求，不够直接有效。",
        "dialogueMode": "user_asks",
        "scenarioHint": "你在兑换点想礼貌地请求将美元兑换成欧元，需要先向工作人员发起对话"
      }
    },
    {
      "id": "travel_066_sub_1_choice_2",
      "subSceneId": "travel_066_sub_1",
      "type": "choice",
      "order": 2,
      "content": {
        "qaId": null,
        "type": "choice",
        "options": [
          {
            "id": "opt_1",
            "text": "I need to change pounds to yen now.",
            "isCorrect": false
          },
          {
            "id": "opt_2",
            "text": "Can I swap pounds for yen?",
            "isCorrect": false
          },
          {
            "id": "opt_3",
            "text": "Could I convert some pounds into yen?",
            "isCorrect": true
          },
          {
            "id": "opt_4",
            "text": "You change pounds to yen?",
            "isCorrect": false
          }
        ],
        "explanation": "正确答案 'Could I convert...' 是礼貌且地道的请求表达，'convert' 是兑换货币的正式动词。选项1 'I need' 显得急迫且不礼貌；选项2 'swap' 虽意思接近，但口语中较少用于货币兑换；选项4是错误的疑问句结构，不符合英语语法规则。",
        "speakerText": "Hello, I'd like to change some pounds into yen. Is that possible?",
        "dialogueMode": "user_responds",
        "speakerTextCn": "您好，我想把一些英镑换成日元，可以吗？"
      }
    },
    {
      "id": "travel_066_sub_1_choice_3",
      "subSceneId": "travel_066_sub_1",
      "type": "choice",
      "order": 3,
      "content": {
        "qaId": null,
        "type": "choice",
        "options": [
          {
            "id": "opt_1",
            "text": "I want to trade CAD for AUD.",
            "isCorrect": false
          },
          {
            "id": "opt_2",
            "text": "Can you exchange CAD for AUD for me?",
            "isCorrect": true
          },
          {
            "id": "opt_3",
            "text": "Exchange CAD to AUD, please.",
            "isCorrect": false
          },
          {
            "id": "opt_4",
            "text": "Do you accept CAD for AUD?",
            "isCorrect": false
          }
        ],
        "explanation": "正确答案 'Can you exchange... for me?' 是礼貌请求的常见变体，把请求对象从自己转向对方，更显礼貌和自然。选项1 'I want' 不礼貌；选项3是命令式，缺乏礼貌；选项4询问的是服务是否接受，而非提出兑换请求，语义不符。",
        "speakerText": "Good afternoon. May I exchange Canadian dollars for Australian dollars?",
        "dialogueMode": "user_responds",
        "speakerTextCn": "下午好，我可以把加元换成澳元吗？"
      }
    }
  ]
}