{
  "subSceneId": "travel_070_sub_5",
  "subSceneName": "道别确认",
  "questionType": "speaking",
  "exportedAt": "2026-03-08T15:38:57.256Z",
  "questions": [
    {
      "id": "travel_070_sub_5_speaking_1",
      "subSceneId": "travel_070_sub_5",
      "type": "speaking",
      "order": 1,
      "content": {
        "qaId": "travel_070_sub_5_qa_1",
        "type": "speaking",
        "speakerText": "Your new flight is confirmed for the 15th at 10 a.m. You'll get an email shortly.",
        "dialogueMode": "user_responds",
        "speakerTextCn": "您的新航班已确认，15号上午10点，稍后会发邮件。",
        "expectedAnswers": [
          "Thank you so much! I really appreciate it.",
          "Got it, thanks a lot. Bye!",
          "That’s perfect — thank you for your help. Have a nice day!"
        ],
        "evaluationCriteria": [
          "意图达成度：是否明确表达感谢并确认信息已接收",
          "语言准确性：语法正确，无明显错误",
          "表达自然度：符合口语习惯，语气礼貌且不拖沓",
          "关键词覆盖：使用了 thank / appreciate / got it / bye 等场景关键词"
        ]
      }
    },
    {
      "id": "travel_070_sub_5_speaking_2",
      "subSceneId": "travel_070_sub_5",
      "type": "speaking",
      "order": 2,
      "content": {
        "qaId": null,
        "type": "speaking",
        "speakerText": "All changes have been successfully processed. Your updated itinerary is now confirmed.",
        "dialogueMode": "user_responds",
        "speakerTextCn": "所有变更已成功处理，您的更新行程已确认。",
        "expectedAnswers": [
          "Great! Thanks for your help. Bye!",
          "Appreciate it. I’ll check my email soon.",
          "Perfect — thank you so much. Have a good one!"
        ],
        "evaluationCriteria": [
          "意图达成度：是否清晰表达感谢并结束对话，未提出新问题",
          "语言准确性：用词和结构符合口语规范",
          "表达自然度：语调自然，符合真实对话节奏",
          "关键词覆盖：使用了 appreciate / thank / bye / perfect / great 等道别关键词"
        ]
      }
    },
    {
      "id": "travel_070_sub_5_speaking_3",
      "subSceneId": "travel_070_sub_5",
      "type": "speaking",
      "order": 3,
      "content": {
        "qaId": null,
        "type": "speaking",
        "speakerText": "Your ticket has been reissued. You’re all set for your trip.",
        "dialogueMode": "user_responds",
        "speakerTextCn": "您的机票已重开，您的行程已安排妥当。",
        "expectedAnswers": [
          "Thank you! That’s a relief.",
          "Confirmed! Thanks a bunch. See you on the plane!",
          "Awesome — I really appreciate your help. Goodbye!"
        ],
        "evaluationCriteria": [
          "意图达成度：是否传达感激之情并自然结束通话",
          "语言准确性：语法正确，用词恰当",
          "表达自然度：语气真诚、口语化，符合服务结束场景",
          "关键词覆盖：使用了 thank / appreciate / confirmed / relief / goodbye 等核心表达"
        ]
      }
    }
  ]
}