{
  "subSceneId": "workplace_036_sub_2",
  "subSceneName": "周末闲聊",
  "questionType": "fill_blank",
  "exportedAt": "2026-03-14T13:52:45.002Z",
  "questions": [
    {
      "id": "workplace_036_sub_2_fill_blank_1",
      "subSceneId": "workplace_036_sub_2",
      "type": "fill_blank",
      "order": 1,
      "content": {
        "hint": "描述过去发生的活动，用一般过去时，搭配 'go out' 表示外出活动",
        "type": "fill_blank",
        "blanks": [
          {
            "index": 0,
            "answer": "went out",
            "options": [
              "went out",
              "go out",
              "have gone out",
              "going out"
            ]
          }
        ],
        "situation": "周末结束后，同事在办公室闲聊，询问你上周末的安排",
        "speakerText": "So, what did you get up to this weekend?",
        "dialogueMode": "user_responds",
        "speakerTextCn": "那么，这周末你做什么了？",
        "knowledgePoint": "一般过去时表达周末活动",
        "responseTemplate": "I ___ with some friends."
      }
    }
  ]
}