{
  "subSceneId": "workplace_033_sub_5",
  "subSceneName": "结束沟通",
  "questionType": "speaking",
  "exportedAt": "2026-03-08T15:38:57.371Z",
  "questions": [
    {
      "id": "workplace_033_sub_5_speaking_1",
      "subSceneId": "workplace_033_sub_5",
      "type": "speaking",
      "order": 1,
      "content": {
        "qaId": "workplace_033_sub_5_qa_1",
        "type": "speaking",
        "speakerText": "Alright, I've sent everything—let me know if you need anything else.",
        "dialogueMode": "user_responds",
        "speakerTextCn": "好了，都发了，有需要随时说。",
        "expectedAnswers": [
          "Thanks! I'll review it by tomorrow and get back to you.",
          "Appreciate it—have a great afternoon!",
          "Got it, thanks so much!"
        ],
        "evaluationCriteria": [
          "意图达成度：是否明确回应了对方的善意并承诺后续行动或表达感谢",
          "语言准确性：语法正确，无明显错误",
          "表达自然度：是否使用了符合职场语境的口语表达"
        ]
      }
    },
    {
      "id": "workplace_033_sub_5_speaking_2",
      "subSceneId": "workplace_033_sub_5",
      "type": "speaking",
      "order": 2,
      "content": {
        "qaId": "workplace_033_sub_5_qa_2",
        "type": "speaking",
        "speakerText": "Just confirming—we're all set on the email? No changes needed?",
        "dialogueMode": "user_responds",
        "speakerTextCn": "确认一下，邮件没问题了吧？不需要改了？",
        "expectedAnswers": [
          "All clear. Thanks for your help!",
          "Perfect—everything looks good.",
          "Actually, could you add the Q3 forecast slide? Just one more."
        ],
        "evaluationCriteria": [
          "意图达成度：是否准确回应了‘确认无变更’的意图，或礼貌提出合理修改",
          "语言准确性：用词和结构符合职场沟通规范",
          "关键词覆盖：是否使用了 'all clear', 'looks good', 或 'add' 等场景关键词"
        ]
      }
    }
  ]
}